label_noise_correction/__init__.py
label_noise_correction/be.py
label_noise_correction/cc.py
label_noise_correction/fair_obnc.py
label_noise_correction/hlnc.py
label_noise_correction/labelcorrection.py
label_noise_correction/obnc.py
label_noise_correction/pl.py
label_noise_correction/stc.py
label_noise_correction-0.0.4.dist-info/METADATA
label_noise_correction-0.0.4.dist-info/WHEEL
label_noise_correction-0.0.4.dist-info/licenses/LICENSE
label_noise_correction-0.0.4.dist-info/RECORD
