Metadata-Version: 2.1
Name: label_noise_correction
Version: 0.0.4
Summary: Label Noise Correction Methods
Project-URL: Homepage, https://github.com/reluzita/label-noise-correction
Author-email: Inês Silva <inesoliveiraesilva@gmail.com>
License-File: LICENSE
Classifier: License :: OSI Approved :: MIT License
Classifier: Operating System :: OS Independent
Classifier: Programming Language :: Python :: 3
Requires-Python: >=3.7
